inline_tests/__init__.py
inline_tests/_types.py
inline_tests/cli.py
inline_tests/hatch.py
inline_tests/hatch_hooks.py
inline_tests/plugin.py
inline_tests/py.typed
inline_tests/strip.py
inline_tests-0.1.0.dist-info/WHEEL
inline_tests-0.1.0.dist-info/entry_points.txt
inline_tests-0.1.0.dist-info/METADATA
inline_tests-0.1.0.dist-info/RECORD
