Metadata-Version: 2.3
Name: inline-tests
Version: 0.1.0
Summary: Colocate your Python tests, Rust-style
Keywords: testing,pytest,inline,colocate,rust,tdd
Author: Windsor Nguyen
Author-email: Windsor Nguyen <oss@dedaluslabs.ai>
License: MIT
Classifier: Development Status :: 4 - Beta
Classifier: Framework :: Pytest
Classifier: Intended Audience :: Developers
Classifier: License :: OSI Approved :: MIT License
Classifier: Operating System :: OS Independent
Classifier: Programming Language :: Python :: 3
Classifier: Programming Language :: Python :: 3.10
Classifier: Programming Language :: Python :: 3.11
Classifier: Programming Language :: Python :: 3.12
Classifier: Programming Language :: Python :: 3.13
Classifier: Programming Language :: Python :: 3.14
Classifier: Topic :: Software Development :: Testing
Classifier: Typing :: Typed
Requires-Dist: pytest>=8.0.0
Requires-Dist: pytest-asyncio>=1.0.0 ; extra == 'async'
Requires-Dist: anyio>=4.0.0 ; extra == 'async'
Requires-Dist: pyleak>=0.1.0 ; extra == 'async'
Requires-Dist: pytest-benchmark>=5.0.0 ; extra == 'bench'
Requires-Dist: pytest-cov>=7.0.0 ; extra == 'cov'
Requires-Dist: faker>=37.0.0 ; extra == 'data'
Requires-Dist: inline-tests[async,mock,cov] ; extra == 'essentials'
Requires-Dist: inline-tests[async,mock,cov,parallel,bench,property,http,data] ; extra == 'full'
Requires-Dist: pytest-httpx>=0.35.0 ; extra == 'http'
Requires-Dist: pytest-mock>=3.14.0 ; extra == 'mock'
Requires-Dist: pytest-xdist>=3.5.0 ; extra == 'parallel'
Requires-Dist: hypothesis>=6.100.0 ; extra == 'property'
Maintainer: Dedalus Labs
Maintainer-email: Dedalus Labs <oss@dedaluslabs.ai>
Requires-Python: >=3.10
Project-URL: Homepage, https://github.com/dedalus-labs/inline-tests-python
Project-URL: Documentation, https://oss.dedaluslabs.ai/inline-tests-python
Project-URL: Repository, https://github.com/dedalus-labs/inline-tests-python
Project-URL: Issues, https://github.com/dedalus-labs/inline-tests-python/issues
Provides-Extra: async
Provides-Extra: bench
Provides-Extra: cov
Provides-Extra: data
Provides-Extra: essentials
Provides-Extra: full
Provides-Extra: http
Provides-Extra: mock
Provides-Extra: parallel
Provides-Extra: property
